beg_cli/__init__.py
beg_cli/argsparser.py
beg_cli-0.1.0.dist-info/LICENSE.md
beg_cli-0.1.0.dist-info/METADATA
beg_cli-0.1.0.dist-info/WHEEL
beg_cli-0.1.0.dist-info/RECORD
