Metadata-Version: 2.1
Name: beg-cli
Version: 0.1.0
Summary: The Beginner CLI Tool is a Python-based command-line interface designed to assist newcomers in learning and executing Linux commands interactively. It provides features such as command explanations and scenario-based command suggestions.
Author: Mani Sankar
Author-email: manisankarchintagunti@gmail.com
Requires-Python: >=3.11,<4.0
Classifier: Programming Language :: Python :: 3
Classifier: Programming Language :: Python :: 3.11
Classifier: Programming Language :: Python :: 3.12
Requires-Dist: argparse (>=1.4.0,<2.0.0)
Requires-Dist: configparser (>=6.0.1,<7.0.0)
Requires-Dist: google-generativeai (>=0.4.1,<0.5.0)
Requires-Dist: inquirer (>=3.2.4,<4.0.0)
Requires-Dist: pyfiglet (>=1.0.2,<2.0.0)
Requires-Dist: tabulate (>=0.9.0,<0.10.0)
Requires-Dist: typer (>=0.12.0,<0.13.0)
Requires-Dist: yaspin (>=3.0.1,<4.0.0)
